{
  "learn_learn": {
    "count": 2,
    "success_count": 2,
    "success_rate": 1.0,
    "template": {
      "action": "learn",
      "learning_prompt": "ADHD 스타일 학습 시스템을 만들어줘",
      "auto_execute": true,
      "reason": "Learning intent detected",
      "intent": {
        "type": "learn",
        "content": "ADHD 스타일 학습 시스템을 만들어줘",
        "confidence": 0.8,
        "matched_keywords": [
          "학습"
        ]
      }
    },
    "first_seen": "2025-11-06T16:49:37.315491"
  },
  "create_file_create_file": {
    "count": 5,
    "success_count": 5,
    "success_rate": 1.0,
    "template": {
      "action": "create_file",
      "file_path": "youtube_analyzer.py",
      "content_prompt": "YouTube 분석 시스템 만들어줘 youtube_analyzer.py",
      "auto_execute": true,
      "reason": "File creation intent detected",
      "intent": {
        "type": "create_file",
        "content": "YouTube 분석 시스템 만들어줘 youtube_analyzer.py",
        "confidence": 0.8,
        "matched_keywords": [
          ".py"
        ]
      }
    },
    "first_seen": "2025-11-06T16:52:15.174741"
  }
}